{
  "page": "crew-network",
  "version": 1,
  "seo": {
    "title": "Pilot Network",
    "description": "Pilot and crew profile review organized by airport region, aircraft experience, credential readiness, and assignment suitability."
  },
  "sections": {
    "hero": {
      "enabled": true,
      "eyebrow": "Pilot Network",
      "headline": "Crew coverage reviewed by aircraft, role, and assignment.",
      "body": "AMG Aviation organizes crew support by region, aircraft experience, credential readiness, and support scope. Coverage indicators do not guarantee immediate assignment.",
      "primaryCtaLabel": "Join Pilot Network",
      "primaryCtaHref": "/crew-network/apply",
      "secondaryCtaLabel": "Member Login",
      "secondaryCtaHref": "/login",
      "imageKey": "generatedCrewMap"
    }
  }
}
